frag2text.py
frag2text-0.0.6.dist-info/DESCRIPTION.rst
frag2text-0.0.6.dist-info/METADATA
frag2text-0.0.6.dist-info/metadata.json
frag2text-0.0.6.dist-info/RECORD
frag2text-0.0.6.dist-info/top_level.txt
frag2text-0.0.6.dist-info/WHEEL
