Metadata-Version: 2.0
Name: frag2text
Version: 0.0.6
Summary: Select and reverse-Markdown (html2text) web page fragments.
Home-page: https://github.com/siznax/frag2text/
Author: Steve @siznax
Author-email: steve@siznax.net
License: MIT
Platform: UNKNOWN
Classifier: Development Status :: 2 - Pre-Alpha
Classifier: Intended Audience :: Developers
Classifier: License :: OSI Approved :: MIT License
Classifier: Operating System :: OS Independent
Classifier: Programming Language :: Python
Classifier: Programming Language :: Python :: 2.6
Classifier: Programming Language :: Python :: 2.7
Classifier: Programming Language :: Python :: 3
Classifier: Programming Language :: Python :: 3.3
Requires-Dist: cssselect
Requires-Dist: html2text
Requires-Dist: html5lib
Requires-Dist: lxml
Requires-Dist: requests
